lib_layered_config/__init__.py
lib_layered_config/__init__conf__.py
lib_layered_config/__main__.py
lib_layered_config/_layers.py
lib_layered_config/_platform.py
lib_layered_config/core.py
lib_layered_config/observability.py
lib_layered_config/py.typed
lib_layered_config/testing.py
lib_layered_config/adapters/__init__.py
lib_layered_config/adapters/_nested_keys.py
lib_layered_config/adapters/display/__init__.py
lib_layered_config/adapters/display/rich.py
lib_layered_config/adapters/dotenv/__init__.py
lib_layered_config/adapters/dotenv/default.py
lib_layered_config/adapters/env/__init__.py
lib_layered_config/adapters/env/default.py
lib_layered_config/adapters/file_loaders/__init__.py
lib_layered_config/adapters/file_loaders/_dot_d.py
lib_layered_config/adapters/file_loaders/structured.py
lib_layered_config/adapters/path_resolvers/__init__.py
lib_layered_config/adapters/path_resolvers/_base.py
lib_layered_config/adapters/path_resolvers/_dotenv.py
lib_layered_config/adapters/path_resolvers/_linux.py
lib_layered_config/adapters/path_resolvers/_macos.py
lib_layered_config/adapters/path_resolvers/_windows.py
lib_layered_config/adapters/path_resolvers/default.py
lib_layered_config/application/__init__.py
lib_layered_config/application/merge.py
lib_layered_config/application/ports.py
lib_layered_config/cli/__init__.py
lib_layered_config/cli/common.py
lib_layered_config/cli/constants.py
lib_layered_config/cli/deploy.py
lib_layered_config/cli/fail.py
lib_layered_config/cli/generate.py
lib_layered_config/cli/info.py
lib_layered_config/cli/read.py
lib_layered_config/domain/__init__.py
lib_layered_config/domain/config.py
lib_layered_config/domain/errors.py
lib_layered_config/domain/identifiers.py
lib_layered_config/domain/permissions.py
lib_layered_config/domain/redaction.py
lib_layered_config/examples/__init__.py
lib_layered_config/examples/deploy.py
lib_layered_config/examples/generate.py
lib_layered_config-5.4.0.dist-info/METADATA
lib_layered_config-5.4.0.dist-info/WHEEL
lib_layered_config-5.4.0.dist-info/entry_points.txt
lib_layered_config-5.4.0.dist-info/licenses/LICENSE
lib_layered_config-5.4.0.dist-info/RECORD
