Metadata-Version: 2.4
Name: lib_layered_config
Version: 5.4.0
Summary: Cross-platform layered configuration loader for Python
Project-URL: Homepage, https://github.com/bitranox/lib_layered_config
Project-URL: Repository, https://github.com/bitranox/lib_layered_config.git
Project-URL: Issues, https://github.com/bitranox/lib_layered_config/issues
Author-email: bitranox <bitranox@gmail.com>
License: MIT
License-File: LICENSE
Keywords: configuration,dotenv,env,layered,toml
Classifier: License :: OSI Approved :: MIT License
Classifier: Operating System :: OS Independent
Classifier: Programming Language :: Python :: 3
Classifier: Programming Language :: Python :: 3 :: Only
Classifier: Programming Language :: Python :: 3.10
Classifier: Programming Language :: Python :: 3.11
Classifier: Programming Language :: Python :: 3.12
Classifier: Programming Language :: Python :: 3.13
Classifier: Programming Language :: Python :: 3.14
Classifier: Typing :: Typed
Requires-Python: >=3.10
Requires-Dist: lib-cli-exit-tools>=2.2.4
Requires-Dist: orjson>=3.11.6
Requires-Dist: rich-click>=1.9.7
Requires-Dist: rtoml>=0.13.0
Provides-Extra: dev
Requires-Dist: bandit>=1.9.3; extra == 'dev'
Requires-Dist: build>=1.4.0; extra == 'dev'
Requires-Dist: codecov-cli>=11.2.6; extra == 'dev'
Requires-Dist: coverage[toml]>=7.13.2; extra == 'dev'
Requires-Dist: httpx>=0.28.1; extra == 'dev'
Requires-Dist: hypothesis>=6.151.4; extra == 'dev'
Requires-Dist: import-linter>=2.9; extra == 'dev'
Requires-Dist: pip-audit>=2.10.0; extra == 'dev'
Requires-Dist: pyright[nodejs]>=1.1.408; extra == 'dev'
Requires-Dist: pytest-asyncio>=1.3.0; extra == 'dev'
Requires-Dist: pytest-cov>=7.0.0; extra == 'dev'
Requires-Dist: pytest>=9.0.2; extra == 'dev'
Requires-Dist: pyyaml>=6.0.3; extra == 'dev'
Requires-Dist: ruff>=0.14.14; extra == 'dev'
Requires-Dist: textual>=7.5.0; extra == 'dev'
Requires-Dist: twine>=6.2.0; extra == 'dev'
Provides-Extra: yaml
Requires-Dist: pyyaml>=6.0.3; extra == 'yaml'
